[{"id": 45225184, "epoch_second": 1693746902, "problem_id": "past202012_a", "contest_id": "past202012-open", "user_id": "Balut", "language": "PyPy3 (7.3.0)", "point": 9.0, "length": 167, "result": "AC", "execution_time": 62}, {"id": 45225245, "epoch_second": 1693747026, "problem_id": "past202012_a", "contest_id": "past202012-open", "user_id": "Balut", "language": "PyPy3 (7.3.0)", "point": 9.0, "length": 167, "result": "AC", "execution_time": 64}, {"id": 45225493, "epoch_second": 1693747576, "problem_id": "past202012_a", "contest_id": "past202012-open", "user_id": "Balut", "language": "PyPy3 (7.3.0)", "point": 9.0, "length": 167, "result": "AC", "execution_time": 70}, {"id": 45225606, "epoch_second": 1693747835, "problem_id": "past202012_a", "contest_id": "past202012-open", "user_id": "Balut", "language": "PyPy3 (7.3.0)", "point": 9.0, "length": 167, "result": "AC", "execution_time": 60}, {"id": 45226879, "epoch_second": 1693750842, "problem_id": "past202012_a", "contest_id": "past202012-open", "user_id": "Balut", "language": "PyPy3 (7.3.0)", "point": 9.0, "length": 167, "result": "AC", "execution_time": 231}, {"id": 45227783, "epoch_second": 1693753266, "problem_id": "past202012_a", "contest_id": "past202012-open", "user_id": "Balut", "language": "PyPy3 (7.3.0)", "point": 9.0, "length": 167, "result": "AC", "execution_time": 83}]